setup.py
gh2conf/__init__.py
gh2conf/__main__.py
gh2conf/confluence.py
gh2conf/convert.py
gh2conf/project.py
gh2conf.egg-info/PKG-INFO
gh2conf.egg-info/SOURCES.txt
gh2conf.egg-info/dependency_links.txt
gh2conf.egg-info/pbr.json
gh2conf.egg-info/requires.txt
gh2conf.egg-info/top_level.txt